angola/__init__.py
angola/database.py
angola/dict_mutator.py
angola/dict_query.py
angola/lib.py
angola/lib_dict.py
angola/lib_xql.py
angola-0.17.0.dist-info/LICENSE
angola-0.17.0.dist-info/METADATA
angola-0.17.0.dist-info/WHEEL
angola-0.17.0.dist-info/top_level.txt
angola-0.17.0.dist-info/RECORD
