Metadata-Version: 2.1
Name: angola
Version: 0.17.0
Summary: angola 
Home-page: https://github.com/mardix/angola
Author: Mardix
Author-email: mardix@blackdevhub.io
Classifier: Programming Language :: Python :: 3
Classifier: License :: OSI Approved :: MIT License
Classifier: Topic :: Database
Requires-Python: >=3.8.0
License-File: LICENSE
Requires-Dist: cuid2
Requires-Dist: Jinja2 >=3.0
Requires-Dist: python-slugify
Requires-Dist: arrow
Requires-Dist: python-arango
